phenotastic/__init__.py
phenotastic/domains.py
phenotastic/mesh.py
phenotastic/misc.py
phenotastic-0.3.0.dist-info/AUTHORS.rst
phenotastic-0.3.0.dist-info/LICENSE
phenotastic-0.3.0.dist-info/METADATA
phenotastic-0.3.0.dist-info/WHEEL
phenotastic-0.3.0.dist-info/top_level.txt
phenotastic-0.3.0.dist-info/RECORD
