Metadata-Version: 2.1
Name: phenotastic
Version: 0.3.0
Summary: 3D plant phenotyping.
Home-page: https://github.com/supersubscript/phenotastic
Author: Henrik Ahl
Author-email: hpa22@cam.ac.uk
License: GNU General Public License v3
Keywords: phenotastic
Classifier: Development Status :: 2 - Pre-Alpha
Classifier: Intended Audience :: Developers
Classifier: License :: OSI Approved :: GNU General Public License v3 (GPLv3)
Classifier: Natural Language :: English
Classifier: Programming Language :: Python :: 3.9
License-File: LICENSE
License-File: AUTHORS.rst
Requires-Dist: vtk (>=9)
Requires-Dist: pyvista (>=0.36.1)
Requires-Dist: pystackreg (>=0.2.2)
Requires-Dist: pymeshfix (>=0.16.1)
Requires-Dist: pyacvd (>=0.2.8)
Requires-Dist: pyvistaqt (>=0.9.0)
Requires-Dist: clahe (>=0.1)
Requires-Dist: imgmisc (>=0.1.17)
Requires-Dist: scipy (>=1.7.3)
Requires-Dist: numpy (>=1.21.6)
Requires-Dist: scikit-image (>=0.19.3)
Requires-Dist: mahotas (>=1.4.13)
Requires-Dist: tifffile (>=1.23.1)
Requires-Dist: czifile (>=2019.7.2)
Requires-Dist: flowdec (>=1.1.0)
Requires-Dist: pandas (>=1.3.5)
Requires-Dist: psf (>=2021.6.6)
Requires-Dist: scikit-learn (>=1.1.1)
